LICENSE.txt
MANIFEST.in
README.rst
setup.cfg
setup.py
django_configure/__init__.py
django_configure/admin.py
django_configure/apps.py
django_configure/models.py
django_configure/type.py
django_configure/urls.py
django_configure/views.py
django_configure.egg-info/PKG-INFO
django_configure.egg-info/SOURCES.txt
django_configure.egg-info/dependency_links.txt
django_configure.egg-info/requires.txt
django_configure.egg-info/top_level.txt
django_configure/management/__init__.py
django_configure/management/commands/__init__.py
django_configure/management/commands/createconfig.py
django_configure/migrations/__init__.py
django_configure/resources/wsgi.py.template
django_configure/tests/__init__.py
django_configure/tests/test_commands.py
django_configure/tests/test_config.py
django_configure/tests/testapp/__init__.py
django_configure/tests/testapp/manage.py
django_configure/tests/testapp/settings.py
django_configure/tests/testapp/urls.py
django_configure/tests/testapp/views.py