Metadata-Version: 1.1
Name: django-configure
Version: 0.3.0
Summary: Utility for defining external django configs (for end user)
Home-page: UNKNOWN
Author: Michał Szostak
Author-email: szostak.m.f@gmail.com
License: MIT License
Keywords: configuration,django
Platform: UNKNOWN
Classifier: Environment :: Web Environment
Classifier: Framework :: Django
Classifier: Intended Audience :: Developers
Classifier: License :: OSI Approved :: MIT License
Classifier: Operating System :: OS Independent
Classifier: Programming Language :: Python
Classifier: Topic :: Internet :: WWW/HTTP
Classifier: Topic :: Internet :: WWW/HTTP :: Dynamic Content
